pyscal_rdf/__init__.py
pyscal_rdf/encoder.py
pyscal_rdf/graph.py
pyscal_rdf/json_io.py
pyscal_rdf/properties.py
pyscal_rdf/structure.py
pyscal_rdf/visualize.py
pyscal_rdf/workflow.py
pyscal_rdf/data/asmo.owl
pyscal_rdf/data/cmso.owl
pyscal_rdf/data/element.yml
pyscal_rdf/data/pldo.owl
pyscal_rdf/data/podo.owl
pyscal_rdf/network/__init__.py
pyscal_rdf/network/network.py
pyscal_rdf/network/ontology.py
pyscal_rdf/network/parser.py
pyscal_rdf/network/patch.py
pyscal_rdf/network/term.py
pyscal_rdf-0.2.5.dist-info/LICENSE
pyscal_rdf-0.2.5.dist-info/METADATA
pyscal_rdf-0.2.5.dist-info/WHEEL
pyscal_rdf-0.2.5.dist-info/top_level.txt
pyscal_rdf-0.2.5.dist-info/RECORD
