Metadata-Version: 2.1
Name: pyscal_rdf
Version: 0.2.5
Summary: Ontology based structural manipulation and quering
Home-page: https://pyscal.org
Download-URL: https://github.com/pyscal/pyscal_rdf
Author: Abril Azocar Guzman, Sarath Menon
Author-email: sarath.menon@pyscal.org
Classifier: Programming Language :: Python :: 3
License-File: LICENSE
Requires-Dist: numpy
Requires-Dist: ase
Requires-Dist: rdflib
Requires-Dist: pyyaml
Requires-Dist: graphviz
Requires-Dist: networkx
Requires-Dist: pyscal3
Requires-Dist: spglib
Requires-Dist: pandas
Requires-Dist: owlready2
